encrypy.py
encrypy-0.1.0.dist-info/METADATA
encrypy-0.1.0.dist-info/WHEEL
encrypy-0.1.0.dist-info/entry_points.txt
encrypy-0.1.0.dist-info/top_level.txt
encrypy-0.1.0.dist-info/RECORD
